qblaze/__init__.abi3.so
qblaze/__init__.pyi
qblaze/py.typed
qblaze/qiskit.py
qblaze-0.1.0.dist-info/METADATA
qblaze-0.1.0.dist-info/WHEEL
qblaze-0.1.0.dist-info/top_level.txt
qblaze-0.1.0.dist-info/RECORD
qblaze-0.1.0.dist-info/licenses/LICENSE
