Metadata-Version: 2.4
Name: qblaze
Version: 0.1.0
Keywords: Development Status :: 3 - Alpha,Intended Audience :: Developers,Intended Audience :: Science/Research,License :: OSI Approved :: Apache Software License,Programming Language :: Rust,Programming Language :: C,Programming Language :: Python :: 3.10,Programming Language :: Python :: 3.11,Programming Language :: Python :: 3.12,Programming Language :: Python :: 3.13,Programming Language :: Python :: 3.14,Topic :: Scientific/Engineering :: Quantum Computing,Typing :: Typed
Requires-Python: >=3.10
License-File: LICENSE
Provides-Extra: qiskit
Requires-Dist: qiskit<3.0,>=1.4; extra == "qiskit"
Requires-Dist: numpy<3.0,>=1.26; extra == "qiskit"
Dynamic: license-file
